[
  {
    "Difficulty": "HARD",
    "Title": "First Missing Positive",
    "Frequency": "100.0",
    "Acceptance Rate": "0.40935900229806615",
    "Link": "https://leetcode.com/problems/first-missing-positive",
    "Topics": "Array, Hash Table"
  },
  {
    "Difficulty": "MEDIUM",
    "Title": "Longest Increasing Subsequence",
    "Frequency": "100.0",
    "Acceptance Rate": "0.5755440376573543",
    "Link": "https://leetcode.com/problems/longest-increasing-subsequence",
    "Topics": "Array, Binary Search, Dynamic Programming"
  }
]