[
  {
    "Difficulty": "HARD",
    "Title": "Trapping Rain Water",
    "Frequency": "100.0",
    "Acceptance Rate": "0.6481367255379713",
    "Link": "https://leetcode.com/problems/trapping-rain-water",
    "Topics": "Array, Two Pointers, Dynamic Programming, Stack, Monotonic Stack"
  },
  {
    "Difficulty": "EASY",
    "Title": "Two Sum",
    "Frequency": "88.3",
    "Acceptance Rate": "0.5554798083476874",
    "Link": "https://leetcode.com/problems/two-sum",
    "Topics": "Array, Hash Table"
  },
  {
    "Difficulty": "MEDIUM",
    "Title": "Group Anagrams",
    "Frequency": "88.3",
    "Acceptance Rate": "0.7072429805803432",
    "Link": "https://leetcode.com/problems/group-anagrams",
    "Topics": "Array, Hash Table, String, Sorting"
  },
  {
    "Difficulty": "EASY",
    "Title": "Valid Parentheses",
    "Frequency": "88.3",
    "Acceptance Rate": "0.42160766531503485",
    "Link": "https://leetcode.com/problems/valid-parentheses",
    "Topics": "String, Stack"
  },
  {
    "Difficulty": "MEDIUM",
    "Title": "Longest Substring Without Repeating Characters",
    "Frequency": "88.3",
    "Acceptance Rate": "0.36717161884529675",
    "Link": "https://leetcode.com/problems/longest-substring-without-repeating-characters",
    "Topics": "Hash Table, String, Sliding Window"
  }
]